Module.py
__init__.py
main.py
utils.py
dero-modules/__init__.py
dero-modules/clearpass/__init__.py
dero-modules/clearpass/clearpass.py
dero-modules/clearpass/module.yml
dero-modules/clearpass/temp_webserver.py
dero-modules/clearpass/utils.py
dero-modules/clearpass/webserver-process.py
aruba_dero-1.0.7.dist-info/METADATA
aruba_dero-1.0.7.dist-info/WHEEL
aruba_dero-1.0.7.dist-info/entry_points.txt
aruba_dero-1.0.7.dist-info/top_level.txt
aruba_dero-1.0.7.dist-info/RECORD
