Metadata-Version: 2.1
Name: aruba-dero
Version: 1.0.7
Summary: DEmo ROllout helper - Modular Tool to automate demo rollouts
Author-email: Lukas Lanzner <lukas.lanzner@hpe.com>
Requires-Python: >=3.12
Requires-Dist: pyclearpass >=1.0.4
Requires-Dist: psutil ~=5.9.8
Requires-Dist: pyyaml ~=6.0.1
Requires-Dist: cryptography ~=42.0.5
Requires-Dist: winBullet ~=1.1
Requires-Dist: setuptools ~=69.2.0
